{
"DNK":{"Happiness":{"2016":7.526},"Economy":{"2016":1.44178},"Family":{"2016":1.16374},"Health":{"2016":0.79504},"Freedom":{"2016":0.57941},"Trust":{"2016":0.44453},"Generosity":{"2016":0.36171},"Residual":{"2016":2.73939}},
"CHE":{"Happiness":{"2016":7.509},"Economy":{"2016":1.52733},"Family":{"2016":1.14524},"Health":{"2016":0.86303},"Freedom":{"2016":0.58557},"Trust":{"2016":0.41203},"Generosity":{"2016":0.28083},"Residual":{"2016":2.69463}},
"ISL":{"Happiness":{"2016":7.501},"Economy":{"2016":1.42666},"Family":{"2016":1.18326},"Health":{"2016":0.86733},"Freedom":{"2016":0.56624},"Trust":{"2016":0.14975},"Generosity":{"2016":0.47678},"Residual":{"2016":2.83137}},
"NOR":{"Happiness":{"2016":7.498},"Economy":{"2016":1.57744},"Family":{"2016":1.1269},"Health":{"2016":0.79579},"Freedom":{"2016":0.59609},"Trust":{"2016":0.35776},"Generosity":{"2016":0.37895},"Residual":{"2016":2.66465}},
"FIN":{"Happiness":{"2016":7.413},"Economy":{"2016":1.40598},"Family":{"2016":1.13464},"Health":{"2016":0.81091},"Freedom":{"2016":0.57104},"Trust":{"2016":0.41004},"Generosity":{"2016":0.25492},"Residual":{"2016":2.82596}},
"CAN":{"Happiness":{"2016":7.404},"Economy":{"2016":1.44015},"Family":{"2016":1.0961},"Health":{"2016":0.8276},"Freedom":{"2016":0.5737},"Trust":{"2016":0.31329},"Generosity":{"2016":0.44834},"Residual":{"2016":2.70485}},
"NLD":{"Happiness":{"2016":7.339},"Economy":{"2016":1.46468},"Family":{"2016":1.02912},"Health":{"2016":0.81231},"Freedom":{"2016":0.55211},"Trust":{"2016":0.29927},"Generosity":{"2016":0.47416},"Residual":{"2016":2.70749}},
"NZL":{"Happiness":{"2016":7.334},"Economy":{"2016":1.36066},"Family":{"2016":1.17278},"Health":{"2016":0.83096},"Freedom":{"2016":0.58147},"Trust":{"2016":0.41904},"Generosity":{"2016":0.49401},"Residual":{"2016":2.47553}},
"AUS":{"Happiness":{"2016":7.313},"Economy":{"2016":1.44443},"Family":{"2016":1.10476},"Health":{"2016":0.8512},"Freedom":{"2016":0.56837},"Trust":{"2016":0.32331},"Generosity":{"2016":0.47407},"Residual":{"2016":2.5465}},
"SWE":{"Happiness":{"2016":7.291},"Economy":{"2016":1.45181},"Family":{"2016":1.08764},"Health":{"2016":0.83121},"Freedom":{"2016":0.58218},"Trust":{"2016":0.40867},"Generosity":{"2016":0.38254},"Residual":{"2016":2.54734}},
"ISR":{"Happiness":{"2016":7.267},"Economy":{"2016":1.33766},"Family":{"2016":0.99537},"Health":{"2016":0.84917},"Freedom":{"2016":0.36432},"Trust":{"2016":0.08728},"Generosity":{"2016":0.32288},"Residual":{"2016":3.31029}},
"AUT":{"Happiness":{"2016":7.119},"Economy":{"2016":1.45038},"Family":{"2016":1.08383},"Health":{"2016":0.80565},"Freedom":{"2016":0.54355},"Trust":{"2016":0.21348},"Generosity":{"2016":0.32865},"Residual":{"2016":2.69343}},
"USA":{"Happiness":{"2016":7.104},"Economy":{"2016":1.50796},"Family":{"2016":1.04782},"Health":{"2016":0.779},"Freedom":{"2016":0.48163},"Trust":{"2016":0.14868},"Generosity":{"2016":0.41077},"Residual":{"2016":2.72782}},
"CRI":{"Happiness":{"2016":7.087},"Economy":{"2016":1.06879},"Family":{"2016":1.02152},"Health":{"2016":0.76146},"Freedom":{"2016":0.55225},"Trust":{"2016":0.10547},"Generosity":{"2016":0.22553},"Residual":{"2016":3.35168}},
"PRI":{"Happiness":{"2016":7.039},"Economy":{"2016":1.35943},"Family":{"2016":1.08113},"Health":{"2016":0.77758},"Freedom":{"2016":0.46823},"Trust":{"2016":0.12275},"Generosity":{"2016":0.22202},"Residual":{"2016":3.0076}},
"DEU":{"Happiness":{"2016":6.994},"Economy":{"2016":1.44787},"Family":{"2016":1.09774},"Health":{"2016":0.81487},"Freedom":{"2016":0.53466},"Trust":{"2016":0.28551},"Generosity":{"2016":0.30452},"Residual":{"2016":2.50931}},
"BRA":{"Happiness":{"2016":6.952},"Economy":{"2016":1.08754},"Family":{"2016":1.03938},"Health":{"2016":0.61415},"Freedom":{"2016":0.40425},"Trust":{"2016":0.14166},"Generosity":{"2016":0.15776},"Residual":{"2016":3.50733}},
"BEL":{"Happiness":{"2016":6.929},"Economy":{"2016":1.42539},"Family":{"2016":1.05249},"Health":{"2016":0.81959},"Freedom":{"2016":0.51354},"Trust":{"2016":0.26248},"Generosity":{"2016":0.2424},"Residual":{"2016":2.61355}},
"IRL":{"Happiness":{"2016":6.907},"Economy":{"2016":1.48341},"Family":{"2016":1.16157},"Health":{"2016":0.81455},"Freedom":{"2016":0.54008},"Trust":{"2016":0.29754},"Generosity":{"2016":0.44963},"Residual":{"2016":2.15988}},
"LUX":{"Happiness":{"2016":6.871},"Economy":{"2016":1.69752},"Family":{"2016":1.03999},"Health":{"2016":0.84542},"Freedom":{"2016":0.5487},"Trust":{"2016":0.35329},"Generosity":{"2016":0.27571},"Residual":{"2016":2.11055}},
"MEX":{"Happiness":{"2016":6.778},"Economy":{"2016":1.11508},"Family":{"2016":0.7146},"Health":{"2016":0.71143},"Freedom":{"2016":0.37709},"Trust":{"2016":0.18355},"Generosity":{"2016":0.11735},"Residual":{"2016":3.55906}},
"SGP":{"Happiness":{"2016":6.739},"Economy":{"2016":1.64555},"Family":{"2016":0.86758},"Health":{"2016":0.94719},"Freedom":{"2016":0.4877},"Trust":{"2016":0.46987},"Generosity":{"2016":0.32706},"Residual":{"2016":1.99375}},
"GBR":{"Happiness":{"2016":6.725},"Economy":{"2016":1.40283},"Family":{"2016":1.08672},"Health":{"2016":0.80991},"Freedom":{"2016":0.50036},"Trust":{"2016":0.27399},"Generosity":{"2016":0.50156},"Residual":{"2016":2.14999}},
"CHL":{"Happiness":{"2016":6.705},"Economy":{"2016":1.2167},"Family":{"2016":0.90587},"Health":{"2016":0.81883},"Freedom":{"2016":0.37789},"Trust":{"2016":0.11451},"Generosity":{"2016":0.31595},"Residual":{"2016":2.95505}},
"PAN":{"Happiness":{"2016":6.701},"Economy":{"2016":1.18306},"Family":{"2016":0.98912},"Health":{"2016":0.70835},"Freedom":{"2016":0.48927},"Trust":{"2016":0.08423},"Generosity":{"2016":0.2418},"Residual":{"2016":3.00559}},
"ARG":{"Happiness":{"2016":6.65},"Economy":{"2016":1.15137},"Family":{"2016":1.06612},"Health":{"2016":0.69711},"Freedom":{"2016":0.42284},"Trust":{"2016":0.07296},"Generosity":{"2016":0.10989},"Residual":{"2016":3.12985}},
"CZE":{"Happiness":{"2016":6.596},"Economy":{"2016":1.30915},"Family":{"2016":1.00793},"Health":{"2016":0.76376},"Freedom":{"2016":0.41418},"Trust":{"2016":0.03986},"Generosity":{"2016":0.09929},"Residual":{"2016":2.96211}},
"ARE":{"Happiness":{"2016":6.573},"Economy":{"2016":1.57352},"Family":{"2016":0.87114},"Health":{"2016":0.72993},"Freedom":{"2016":0.56215},"Trust":{"2016":0.35561},"Generosity":{"2016":0.26591},"Residual":{"2016":2.21507}},
"URY":{"Happiness":{"2016":6.545},"Economy":{"2016":1.18157},"Family":{"2016":1.03143},"Health":{"2016":0.72183},"Freedom":{"2016":0.54388},"Trust":{"2016":0.21394},"Generosity":{"2016":0.18056},"Residual":{"2016":2.67139}},
"MLT":{"Happiness":{"2016":6.488},"Economy":{"2016":1.30782},"Family":{"2016":1.09879},"Health":{"2016":0.80315},"Freedom":{"2016":0.54994},"Trust":{"2016":0.17554},"Generosity":{"2016":0.56237},"Residual":{"2016":1.99032}},
"COL":{"Happiness":{"2016":6.481},"Economy":{"2016":1.03032},"Family":{"2016":1.02169},"Health":{"2016":0.59659},"Freedom":{"2016":0.44735},"Trust":{"2016":0.05399},"Generosity":{"2016":0.15626},"Residual":{"2016":3.17471}},
"FRA":{"Happiness":{"2016":6.478},"Economy":{"2016":1.39488},"Family":{"2016":1.00508},"Health":{"2016":0.83795},"Freedom":{"2016":0.46562},"Trust":{"2016":0.17808},"Generosity":{"2016":0.1216},"Residual":{"2016":2.4744}},
"THA":{"Happiness":{"2016":6.474},"Economy":{"2016":1.0893},"Family":{"2016":1.04477},"Health":{"2016":0.64915},"Freedom":{"2016":0.49553},"Trust":{"2016":0.02833},"Generosity":{"2016":0.58696},"Residual":{"2016":2.5796}},
"SAU":{"Happiness":{"2016":6.379},"Economy":{"2016":1.48953},"Family":{"2016":0.84829},"Health":{"2016":0.59267},"Freedom":{"2016":0.37904},"Trust":{"2016":0.30008},"Generosity":{"2016":0.15457},"Residual":{"2016":2.61482}},
"TWN":{"Happiness":{"2016":6.379},"Economy":{"2016":1.39729},"Family":{"2016":0.92624},"Health":{"2016":0.79565},"Freedom":{"2016":0.32377},"Trust":{"2016":0.0663},"Generosity":{"2016":0.25495},"Residual":{"2016":2.61523}},
"QAT":{"Happiness":{"2016":6.375},"Economy":{"2016":1.82427},"Family":{"2016":0.87964},"Health":{"2016":0.71723},"Freedom":{"2016":0.56679},"Trust":{"2016":0.48049},"Generosity":{"2016":0.32388},"Residual":{"2016":1.58224}},
"ESP":{"Happiness":{"2016":6.361},"Economy":{"2016":1.34253},"Family":{"2016":1.12945},"Health":{"2016":0.87896},"Freedom":{"2016":0.37545},"Trust":{"2016":0.06137},"Generosity":{"2016":0.17665},"Residual":{"2016":2.39663}},
"DZA":{"Happiness":{"2016":6.355},"Economy":{"2016":1.05266},"Family":{"2016":0.83309},"Health":{"2016":0.61804},"Freedom":{"2016":0.21006},"Trust":{"2016":0.16157},"Generosity":{"2016":0.07044},"Residual":{"2016":3.40904}},
"GTM":{"Happiness":{"2016":6.324},"Economy":{"2016":0.83454},"Family":{"2016":0.87119},"Health":{"2016":0.54039},"Freedom":{"2016":0.50379},"Trust":{"2016":0.08701},"Generosity":{"2016":0.28808},"Residual":{"2016":3.19863}},
"SUR":{"Happiness":{"2016":6.269},"Economy":{"2016":1.09686},"Family":{"2016":0.77866},"Health":{"2016":0.50933},"Freedom":{"2016":0.52234},"Trust":{"2016":0.12692},"Generosity":{"2016":0.16665},"Residual":{"2016":3.06852}},
"KWT":{"Happiness":{"2016":6.239},"Economy":{"2016":1.61714},"Family":{"2016":0.87758},"Health":{"2016":0.63569},"Freedom":{"2016":0.43166},"Trust":{"2016":0.23669},"Generosity":{"2016":0.15965},"Residual":{"2016":2.28085}},
"BHR":{"Happiness":{"2016":6.218},"Economy":{"2016":1.44024},"Family":{"2016":0.94397},"Health":{"2016":0.65696},"Freedom":{"2016":0.47375},"Trust":{"2016":0.25772},"Generosity":{"2016":0.17147},"Residual":{"2016":2.27405}},
"TTO":{"Happiness":{"2016":6.168},"Economy":{"2016":1.32572},"Family":{"2016":0.98569},"Health":{"2016":0.52608},"Freedom":{"2016":0.48453},"Trust":{"2016":0.01241},"Generosity":{"2016":0.31935},"Residual":{"2016":2.51394}},
"VEN":{"Happiness":{"2016":6.084},"Economy":{"2016":1.13367},"Family":{"2016":1.03302},"Health":{"2016":0.61904},"Freedom":{"2016":0.19847},"Trust":{"2016":0.08304},"Generosity":{"2016":0.0425},"Residual":{"2016":2.97468}},
"SVK":{"Happiness":{"2016":6.078},"Economy":{"2016":1.27973},"Family":{"2016":1.08268},"Health":{"2016":0.70367},"Freedom":{"2016":0.23391},"Trust":{"2016":0.02947},"Generosity":{"2016":0.13837},"Residual":{"2016":2.61065}},
"SLV":{"Happiness":{"2016":6.068},"Economy":{"2016":0.8737},"Family":{"2016":0.80975},"Health":{"2016":0.596},"Freedom":{"2016":0.37269},"Trust":{"2016":0.10613},"Generosity":{"2016":0.08877},"Residual":{"2016":3.22134}},
"MYS":{"Happiness":{"2016":6.005},"Economy":{"2016":1.25142},"Family":{"2016":0.88025},"Health":{"2016":0.62366},"Freedom":{"2016":0.39031},"Trust":{"2016":0.09081},"Generosity":{"2016":0.41474},"Residual":{"2016":2.35384}},
"NIC":{"Happiness":{"2016":5.992},"Economy":{"2016":0.69384},"Family":{"2016":0.89521},"Health":{"2016":0.65213},"Freedom":{"2016":0.46582},"Trust":{"2016":0.16292},"Generosity":{"2016":0.29773},"Residual":{"2016":2.82428}},
"UZB":{"Happiness":{"2016":5.987},"Economy":{"2016":0.73591},"Family":{"2016":1.1681},"Health":{"2016":0.50163},"Freedom":{"2016":0.60848},"Trust":{"2016":0.28333},"Generosity":{"2016":0.34326},"Residual":{"2016":2.34638}},
"ITA":{"Happiness":{"2016":5.977},"Economy":{"2016":1.35495},"Family":{"2016":1.04167},"Health":{"2016":0.85102},"Freedom":{"2016":0.18827},"Trust":{"2016":0.02556},"Generosity":{"2016":0.16684},"Residual":{"2016":2.34918}},
"ECU":{"Happiness":{"2016":5.976},"Economy":{"2016":0.97306},"Family":{"2016":0.85974},"Health":{"2016":0.68613},"Freedom":{"2016":0.4027},"Trust":{"2016":0.18037},"Generosity":{"2016":0.10074},"Residual":{"2016":2.77366}},
"BLZ":{"Happiness":{"2016":5.956},"Economy":{"2016":0.87616},"Family":{"2016":0.68655},"Health":{"2016":0.45569},"Freedom":{"2016":0.51231},"Trust":{"2016":0.10771},"Generosity":{"2016":0.23684},"Residual":{"2016":3.08039}},
"JPN":{"Happiness":{"2016":5.921},"Economy":{"2016":1.38007},"Family":{"2016":1.06054},"Health":{"2016":0.91491},"Freedom":{"2016":0.46761},"Trust":{"2016":0.18985},"Generosity":{"2016":0.10224},"Residual":{"2016":1.80584}},
"KAZ":{"Happiness":{"2016":5.919},"Economy":{"2016":1.22943},"Family":{"2016":0.95544},"Health":{"2016":0.57386},"Freedom":{"2016":0.4052},"Trust":{"2016":0.11132},"Generosity":{"2016":0.15011},"Residual":{"2016":2.49325}},
"MDA":{"Happiness":{"2016":5.897},"Economy":{"2016":0.69177},"Family":{"2016":0.83132},"Health":{"2016":0.52309},"Freedom":{"2016":0.25202},"Trust":{"2016":0.01903},"Generosity":{"2016":0.19997},"Residual":{"2016":3.38007}},
"RUS":{"Happiness":{"2016":5.856},"Economy":{"2016":1.23228},"Family":{"2016":1.05261},"Health":{"2016":0.58991},"Freedom":{"2016":0.32682},"Trust":{"2016":0.03586},"Generosity":{"2016":0.02736},"Residual":{"2016":2.59115}},
"POL":{"Happiness":{"2016":5.835},"Economy":{"2016":1.24585},"Family":{"2016":1.04685},"Health":{"2016":0.69058},"Freedom":{"2016":0.4519},"Trust":{"2016":0.055},"Generosity":{"2016":0.14443},"Residual":{"2016":2.20035}},
"KOR":{"Happiness":{"2016":5.835},"Economy":{"2016":1.35948},"Family":{"2016":0.72194},"Health":{"2016":0.88645},"Freedom":{"2016":0.25168},"Trust":{"2016":0.07716},"Generosity":{"2016":0.18824},"Residual":{"2016":2.35015}},
"BOL":{"Happiness":{"2016":5.822},"Economy":{"2016":0.79422},"Family":{"2016":0.83779},"Health":{"2016":0.4697},"Freedom":{"2016":0.50961},"Trust":{"2016":0.07746},"Generosity":{"2016":0.21698},"Residual":{"2016":2.91635}},
"LTU":{"Happiness":{"2016":5.813},"Economy":{"2016":1.2692},"Family":{"2016":1.06411},"Health":{"2016":0.64674},"Freedom":{"2016":0.18929},"Trust":{"2016":0.0182},"Generosity":{"2016":0.02025},"Residual":{"2016":2.60525}},
"BLR":{"Happiness":{"2016":5.802},"Economy":{"2016":1.13062},"Family":{"2016":1.04993},"Health":{"2016":0.63104},"Freedom":{"2016":0.29091},"Trust":{"2016":0.17457},"Generosity":{"2016":0.13942},"Residual":{"2016":2.38582}},
"NCY":{"Happiness":{"2016":5.771},"Economy":{"2016":1.31141},"Family":{"2016":0.81826},"Health":{"2016":0.84142},"Freedom":{"2016":0.43596},"Trust":{"2016":0.16578},"Generosity":{"2016":0.26322},"Residual":{"2016":1.93447}},
"SVN":{"Happiness":{"2016":5.768},"Economy":{"2016":1.29947},"Family":{"2016":1.05613},"Health":{"2016":0.79151},"Freedom":{"2016":0.53164},"Trust":{"2016":0.03635},"Generosity":{"2016":0.25738},"Residual":{"2016":1.79522}},
"PER":{"Happiness":{"2016":5.743},"Economy":{"2016":0.99602},"Family":{"2016":0.81255},"Health":{"2016":0.62994},"Freedom":{"2016":0.37502},"Trust":{"2016":0.05292},"Generosity":{"2016":0.14527},"Residual":{"2016":2.73117}},
"TKM":{"Happiness":{"2016":5.658},"Economy":{"2016":1.08017},"Family":{"2016":1.03817},"Health":{"2016":0.44006},"Freedom":{"2016":0.37408},"Trust":{"2016":0.28467},"Generosity":{"2016":0.22567},"Residual":{"2016":2.21489}},
"MUS":{"Happiness":{"2016":5.648},"Economy":{"2016":1.14372},"Family":{"2016":0.75695},"Health":{"2016":0.66189},"Freedom":{"2016":0.46145},"Trust":{"2016":0.05203},"Generosity":{"2016":0.36951},"Residual":{"2016":2.20223}},
"LBY":{"Happiness":{"2016":5.615},"Economy":{"2016":1.06688},"Family":{"2016":0.95076},"Health":{"2016":0.52304},"Freedom":{"2016":0.40672},"Trust":{"2016":0.10339},"Generosity":{"2016":0.17087},"Residual":{"2016":2.39374}},
"LVA":{"Happiness":{"2016":5.56},"Economy":{"2016":1.21788},"Family":{"2016":0.95025},"Health":{"2016":0.63952},"Freedom":{"2016":0.27996},"Trust":{"2016":0.0889},"Generosity":{"2016":0.17445},"Residual":{"2016":2.20859}},
"CYP":{"Happiness":{"2016":5.546},"Economy":{"2016":1.31857},"Family":{"2016":0.70697},"Health":{"2016":0.8488},"Freedom":{"2016":0.29507},"Trust":{"2016":0.05228},"Generosity":{"2016":0.27906},"Residual":{"2016":2.04497}},
"PRY":{"Happiness":{"2016":5.538},"Economy":{"2016":0.89373},"Family":{"2016":1.11111},"Health":{"2016":0.58295},"Freedom":{"2016":0.46235},"Trust":{"2016":0.07396},"Generosity":{"2016":0.25296},"Residual":{"2016":2.16091}},
"ROU":{"Happiness":{"2016":5.528},"Economy":{"2016":1.1697},"Family":{"2016":0.72803},"Health":{"2016":0.67602},"Freedom":{"2016":0.36712},"Trust":{"2016":0.00679},"Generosity":{"2016":0.12889},"Residual":{"2016":2.45184}},
"EST":{"Happiness":{"2016":5.517},"Economy":{"2016":1.27964},"Family":{"2016":1.05163},"Health":{"2016":0.68098},"Freedom":{"2016":0.41511},"Trust":{"2016":0.18519},"Generosity":{"2016":0.08423},"Residual":{"2016":1.81985}},
"JAM":{"Happiness":{"2016":5.51},"Economy":{"2016":0.89333},"Family":{"2016":0.96372},"Health":{"2016":0.59469},"Freedom":{"2016":0.43597},"Trust":{"2016":0.04294},"Generosity":{"2016":0.22245},"Residual":{"2016":2.35682}},
"HRV":{"Happiness":{"2016":5.488},"Economy":{"2016":1.18649},"Family":{"2016":0.60809},"Health":{"2016":0.70524},"Freedom":{"2016":0.23907},"Trust":{"2016":0.04002},"Generosity":{"2016":0.18434},"Residual":{"2016":2.52462}},
"HKG":{"Happiness":{"2016":5.458},"Economy":{"2016":1.5107},"Family":{"2016":0.87021},"Health":{"2016":0.95277},"Freedom":{"2016":0.48079},"Trust":{"2016":0.31647},"Generosity":{"2016":0.40097},"Residual":{"2016":0.92614}},
"SOM":{"Happiness":{"2016":5.44},"Economy":{"2016":0},"Family":{"2016":0.33613},"Health":{"2016":0.11466},"Freedom":{"2016":0.56778},"Trust":{"2016":0.3118},"Generosity":{"2016":0.27225},"Residual":{"2016":3.83772}},
"XKX":{"Happiness":{"2016":5.401},"Economy":{"2016":0.90145},"Family":{"2016":0.66062},"Health":{"2016":0.54},"Freedom":{"2016":0.14396},"Trust":{"2016":0.06547},"Generosity":{"2016":0.27992},"Residual":{"2016":2.80998}},
"TUR":{"Happiness":{"2016":5.389},"Economy":{"2016":1.16492},"Family":{"2016":0.87717},"Health":{"2016":0.64718},"Freedom":{"2016":0.23889},"Trust":{"2016":0.12348},"Generosity":{"2016":0.04707},"Residual":{"2016":2.29074}},
"IDN":{"Happiness":{"2016":5.314},"Economy":{"2016":0.95104},"Family":{"2016":0.87625},"Health":{"2016":0.49374},"Freedom":{"2016":0.39237},"Trust":{"2016":0.00322},"Generosity":{"2016":0.56521},"Residual":{"2016":2.03171}},
"JOR":{"Happiness":{"2016":5.303},"Economy":{"2016":0.99673},"Family":{"2016":0.86216},"Health":{"2016":0.60712},"Freedom":{"2016":0.36023},"Trust":{"2016":0.13297},"Generosity":{"2016":0.14262},"Residual":{"2016":2.20142}},
"AZE":{"Happiness":{"2016":5.291},"Economy":{"2016":1.12373},"Family":{"2016":0.76042},"Health":{"2016":0.54504},"Freedom":{"2016":0.35327},"Trust":{"2016":0.17914},"Generosity":{"2016":0.0564},"Residual":{"2016":2.2735}},
"PHL":{"Happiness":{"2016":5.279},"Economy":{"2016":0.81217},"Family":{"2016":0.87877},"Health":{"2016":0.47036},"Freedom":{"2016":0.54854},"Trust":{"2016":0.11757},"Generosity":{"2016":0.21674},"Residual":{"2016":2.23484}},
"CHN":{"Happiness":{"2016":5.245},"Economy":{"2016":1.0278},"Family":{"2016":0.79381},"Health":{"2016":0.73561},"Freedom":{"2016":0.44012},"Trust":{"2016":0.02745},"Generosity":{"2016":0.04959},"Residual":{"2016":2.17087}},
"BTN":{"Happiness":{"2016":5.196},"Economy":{"2016":0.8527},"Family":{"2016":0.90836},"Health":{"2016":0.49759},"Freedom":{"2016":0.46074},"Trust":{"2016":0.1616},"Generosity":{"2016":0.48546},"Residual":{"2016":1.82916}},
"KGZ":{"Happiness":{"2016":5.185},"Economy":{"2016":0.56044},"Family":{"2016":0.95434},"Health":{"2016":0.55449},"Freedom":{"2016":0.40212},"Trust":{"2016":0.04762},"Generosity":{"2016":0.38432},"Residual":{"2016":2.28136}},
"SRB":{"Happiness":{"2016":5.177},"Economy":{"2016":1.03437},"Family":{"2016":0.81329},"Health":{"2016":0.6458},"Freedom":{"2016":0.15718},"Trust":{"2016":0.04339},"Generosity":{"2016":0.20737},"Residual":{"2016":2.27539}},
"BIH":{"Happiness":{"2016":5.163},"Economy":{"2016":0.93383},"Family":{"2016":0.64367},"Health":{"2016":0.70766},"Freedom":{"2016":0.09511},"Trust":{"2016":0},"Generosity":{"2016":0.29889},"Residual":{"2016":2.48406}},
"MNE":{"Happiness":{"2016":5.161},"Economy":{"2016":1.07838},"Family":{"2016":0.74173},"Health":{"2016":0.63533},"Freedom":{"2016":0.15111},"Trust":{"2016":0.12721},"Generosity":{"2016":0.17191},"Residual":{"2016":2.25531}},
"DOM":{"Happiness":{"2016":5.155},"Economy":{"2016":1.02787},"Family":{"2016":0.99496},"Health":{"2016":0.57669},"Freedom":{"2016":0.52259},"Trust":{"2016":0.12372},"Generosity":{"2016":0.21286},"Residual":{"2016":1.69626}},
"MAR":{"Happiness":{"2016":5.151},"Economy":{"2016":0.84058},"Family":{"2016":0.38595},"Health":{"2016":0.59471},"Freedom":{"2016":0.25646},"Trust":{"2016":0.08404},"Generosity":{"2016":0.04053},"Residual":{"2016":2.94891}},
"HUN":{"Happiness":{"2016":5.145},"Economy":{"2016":1.24142},"Family":{"2016":0.93164},"Health":{"2016":0.67608},"Freedom":{"2016":0.1977},"Trust":{"2016":0.04472},"Generosity":{"2016":0.099},"Residual":{"2016":1.95473}},
"PAK":{"Happiness":{"2016":5.132},"Economy":{"2016":0.68816},"Family":{"2016":0.26135},"Health":{"2016":0.40306},"Freedom":{"2016":0.14622},"Trust":{"2016":0.1388},"Generosity":{"2016":0.31185},"Residual":{"2016":3.18286}},
"LBN":{"Happiness":{"2016":5.129},"Economy":{"2016":1.12268},"Family":{"2016":0.64184},"Health":{"2016":0.76171},"Freedom":{"2016":0.26228},"Trust":{"2016":0.03061},"Generosity":{"2016":0.23693},"Residual":{"2016":2.07339}},
"PRT":{"Happiness":{"2016":5.123},"Economy":{"2016":1.27607},"Family":{"2016":0.94367},"Health":{"2016":0.79363},"Freedom":{"2016":0.44727},"Trust":{"2016":0.01521},"Generosity":{"2016":0.11691},"Residual":{"2016":1.53015}},
"MKD":{"Happiness":{"2016":5.121},"Economy":{"2016":1.0193},"Family":{"2016":0.78236},"Health":{"2016":0.64738},"Freedom":{"2016":0.27668},"Trust":{"2016":0.07047},"Generosity":{"2016":0.23507},"Residual":{"2016":2.08947}},
"VNM":{"Happiness":{"2016":5.061},"Economy":{"2016":0.74037},"Family":{"2016":0.79117},"Health":{"2016":0.66157},"Freedom":{"2016":0.55954},"Trust":{"2016":0.11556},"Generosity":{"2016":0.25075},"Residual":{"2016":1.9418}},
"SOM":{"Happiness":{"2016":5.057},"Economy":{"2016":0.25558},"Family":{"2016":0.75862},"Health":{"2016":0.33108},"Freedom":{"2016":0.3913},"Trust":{"2016":0.36794},"Generosity":{"2016":0.51479},"Residual":{"2016":2.43801}},
"TUN":{"Happiness":{"2016":5.045},"Economy":{"2016":0.97724},"Family":{"2016":0.43165},"Health":{"2016":0.59577},"Freedom":{"2016":0.23553},"Trust":{"2016":0.0817},"Generosity":{"2016":0.03936},"Residual":{"2016":2.68413}},
"GRC":{"Happiness":{"2016":5.033},"Economy":{"2016":1.24886},"Family":{"2016":0.75473},"Health":{"2016":0.80029},"Freedom":{"2016":0.05822},"Trust":{"2016":0.04127},"Generosity":{"2016":0},"Residual":{"2016":2.12944}},
"TJK":{"Happiness":{"2016":4.996},"Economy":{"2016":0.48835},"Family":{"2016":0.75602},"Health":{"2016":0.53119},"Freedom":{"2016":0.43408},"Trust":{"2016":0.13509},"Generosity":{"2016":0.25998},"Residual":{"2016":2.39106}},
"MNG":{"Happiness":{"2016":4.907},"Economy":{"2016":0.98853},"Family":{"2016":1.08983},"Health":{"2016":0.55469},"Freedom":{"2016":0.35972},"Trust":{"2016":0.03285},"Generosity":{"2016":0.34539},"Residual":{"2016":1.53586}},
"LAO":{"Happiness":{"2016":4.876},"Economy":{"2016":0.68042},"Family":{"2016":0.5497},"Health":{"2016":0.38291},"Freedom":{"2016":0.52168},"Trust":{"2016":0.22423},"Generosity":{"2016":0.43079},"Residual":{"2016":2.08637}},
"NGA":{"Happiness":{"2016":4.875},"Economy":{"2016":0.75216},"Family":{"2016":0.64498},"Health":{"2016":0.05108},"Freedom":{"2016":0.27854},"Trust":{"2016":0.0305},"Generosity":{"2016":0.23219},"Residual":{"2016":2.88586}},
"HND":{"Happiness":{"2016":4.871},"Economy":{"2016":0.69429},"Family":{"2016":0.75596},"Health":{"2016":0.58383},"Freedom":{"2016":0.26755},"Trust":{"2016":0.06906},"Generosity":{"2016":0.2044},"Residual":{"2016":2.29551}},
"IRN":{"Happiness":{"2016":4.813},"Economy":{"2016":1.11758},"Family":{"2016":0.38857},"Health":{"2016":0.64232},"Freedom":{"2016":0.22544},"Trust":{"2016":0.0557},"Generosity":{"2016":0.38538},"Residual":{"2016":1.99817}},
"ZMB":{"Happiness":{"2016":4.795},"Economy":{"2016":0.61202},"Family":{"2016":0.6376},"Health":{"2016":0.23573},"Freedom":{"2016":0.42662},"Trust":{"2016":0.11479},"Generosity":{"2016":0.17866},"Residual":{"2016":2.58991}},
"NPL":{"Happiness":{"2016":4.793},"Economy":{"2016":0.44626},"Family":{"2016":0.69699},"Health":{"2016":0.50073},"Freedom":{"2016":0.37012},"Trust":{"2016":0.07008},"Generosity":{"2016":0.3816},"Residual":{"2016":2.32694}},
"PSE":{"Happiness":{"2016":4.754},"Economy":{"2016":0.67024},"Family":{"2016":0.71629},"Health":{"2016":0.56844},"Freedom":{"2016":0.17744},"Trust":{"2016":0.10613},"Generosity":{"2016":0.11154},"Residual":{"2016":2.40364}},
"ALB":{"Happiness":{"2016":4.655},"Economy":{"2016":0.9553},"Family":{"2016":0.50163},"Health":{"2016":0.73007},"Freedom":{"2016":0.31866},"Trust":{"2016":0.05301},"Generosity":{"2016":0.1684},"Residual":{"2016":1.92816}},
"BGD":{"Happiness":{"2016":4.643},"Economy":{"2016":0.54177},"Family":{"2016":0.24749},"Health":{"2016":0.52989},"Freedom":{"2016":0.39778},"Trust":{"2016":0.12583},"Generosity":{"2016":0.19132},"Residual":{"2016":2.60904}},
"SLE":{"Happiness":{"2016":4.635},"Economy":{"2016":0.36485},"Family":{"2016":0.628},"Health":{"2016":0},"Freedom":{"2016":0.30685},"Trust":{"2016":0.08196},"Generosity":{"2016":0.23897},"Residual":{"2016":3.01402}},
"IRQ":{"Happiness":{"2016":4.575},"Economy":{"2016":1.07474},"Family":{"2016":0.59205},"Health":{"2016":0.51076},"Freedom":{"2016":0.24856},"Trust":{"2016":0.13636},"Generosity":{"2016":0.19589},"Residual":{"2016":1.81657}},
"NAM":{"Happiness":{"2016":4.574},"Economy":{"2016":0.93287},"Family":{"2016":0.70362},"Health":{"2016":0.34745},"Freedom":{"2016":0.48614},"Trust":{"2016":0.10398},"Generosity":{"2016":0.07795},"Residual":{"2016":1.92198}},
"CMR":{"Happiness":{"2016":4.513},"Economy":{"2016":0.52497},"Family":{"2016":0.62542},"Health":{"2016":0.12698},"Freedom":{"2016":0.42736},"Trust":{"2016":0.06126},"Generosity":{"2016":0.2268},"Residual":{"2016":2.5198}},
"ETH":{"Happiness":{"2016":4.508},"Economy":{"2016":0.29283},"Family":{"2016":0.37932},"Health":{"2016":0.34578},"Freedom":{"2016":0.36703},"Trust":{"2016":0.1717},"Generosity":{"2016":0.29522},"Residual":{"2016":2.65614}},
"ZAF":{"Happiness":{"2016":4.459},"Economy":{"2016":1.02416},"Family":{"2016":0.96053},"Health":{"2016":0.18611},"Freedom":{"2016":0.42483},"Trust":{"2016":0.08415},"Generosity":{"2016":0.13656},"Residual":{"2016":1.64227}},
"LKA":{"Happiness":{"2016":4.415},"Economy":{"2016":0.97318},"Family":{"2016":0.84783},"Health":{"2016":0.62007},"Freedom":{"2016":0.50817},"Trust":{"2016":0.07964},"Generosity":{"2016":0.46978},"Residual":{"2016":0.91681}},
"IND":{"Happiness":{"2016":4.404},"Economy":{"2016":0.74036},"Family":{"2016":0.29247},"Health":{"2016":0.45091},"Freedom":{"2016":0.40285},"Trust":{"2016":0.08722},"Generosity":{"2016":0.25028},"Residual":{"2016":2.18032}},
"MMR":{"Happiness":{"2016":4.395},"Economy":{"2016":0.34112},"Family":{"2016":0.69981},"Health":{"2016":0.3988},"Freedom":{"2016":0.42692},"Trust":{"2016":0.20243},"Generosity":{"2016":0.81971},"Residual":{"2016":1.50655}},
"EGY":{"Happiness":{"2016":4.362},"Economy":{"2016":0.95395},"Family":{"2016":0.49813},"Health":{"2016":0.52116},"Freedom":{"2016":0.18847},"Trust":{"2016":0.10393},"Generosity":{"2016":0.12706},"Residual":{"2016":1.96895}},
"ARM":{"Happiness":{"2016":4.36},"Economy":{"2016":0.86086},"Family":{"2016":0.62477},"Health":{"2016":0.64083},"Freedom":{"2016":0.14037},"Trust":{"2016":0.03616},"Generosity":{"2016":0.07793},"Residual":{"2016":1.97864}},
"KEN":{"Happiness":{"2016":4.356},"Economy":{"2016":0.52267},"Family":{"2016":0.7624},"Health":{"2016":0.30147},"Freedom":{"2016":0.40576},"Trust":{"2016":0.06686},"Generosity":{"2016":0.41328},"Residual":{"2016":1.88326}},
"UKR":{"Happiness":{"2016":4.324},"Economy":{"2016":0.87287},"Family":{"2016":1.01413},"Health":{"2016":0.58628},"Freedom":{"2016":0.12859},"Trust":{"2016":0.01829},"Generosity":{"2016":0.20363},"Residual":{"2016":1.50066}},
"GHA":{"Happiness":{"2016":4.276},"Economy":{"2016":0.63107},"Family":{"2016":0.49353},"Health":{"2016":0.29681},"Freedom":{"2016":0.40973},"Trust":{"2016":0.0326},"Generosity":{"2016":0.21203},"Residual":{"2016":2.2002}},
"COD":{"Happiness":{"2016":4.272},"Economy":{"2016":0.05661},"Family":{"2016":0.80676},"Health":{"2016":0.188},"Freedom":{"2016":0.15602},"Trust":{"2016":0.06075},"Generosity":{"2016":0.25458},"Residual":{"2016":2.74924}},
"GEO":{"Happiness":{"2016":4.252},"Economy":{"2016":0.83792},"Family":{"2016":0.19249},"Health":{"2016":0.64035},"Freedom":{"2016":0.32461},"Trust":{"2016":0.3188},"Generosity":{"2016":0.06786},"Residual":{"2016":1.87031}},
"COG":{"Happiness":{"2016":4.236},"Economy":{"2016":0.77109},"Family":{"2016":0.47799},"Health":{"2016":0.28212},"Freedom":{"2016":0.37938},"Trust":{"2016":0.09753},"Generosity":{"2016":0.12077},"Residual":{"2016":2.10681}},
"SEN":{"Happiness":{"2016":4.219},"Economy":{"2016":0.44314},"Family":{"2016":0.77416},"Health":{"2016":0.40457},"Freedom":{"2016":0.31056},"Trust":{"2016":0.11681},"Generosity":{"2016":0.19103},"Residual":{"2016":1.97861}},
"BGR":{"Happiness":{"2016":4.217},"Economy":{"2016":1.11306},"Family":{"2016":0.92542},"Health":{"2016":0.67806},"Freedom":{"2016":0.21219},"Trust":{"2016":0.00615},"Generosity":{"2016":0.12793},"Residual":{"2016":1.15377}},
"MRT":{"Happiness":{"2016":4.201},"Economy":{"2016":0.61391},"Family":{"2016":0.84142},"Health":{"2016":0.28639},"Freedom":{"2016":0.1268},"Trust":{"2016":0.17955},"Generosity":{"2016":0.22686},"Residual":{"2016":1.9263}},
"ZWE":{"Happiness":{"2016":4.193},"Economy":{"2016":0.35041},"Family":{"2016":0.71478},"Health":{"2016":0.1595},"Freedom":{"2016":0.25429},"Trust":{"2016":0.08582},"Generosity":{"2016":0.18503},"Residual":{"2016":2.4427}},
"MWI":{"Happiness":{"2016":4.156},"Economy":{"2016":0.08709},"Family":{"2016":0.147},"Health":{"2016":0.29364},"Freedom":{"2016":0.4143},"Trust":{"2016":0.07564},"Generosity":{"2016":0.30968},"Residual":{"2016":2.82859}},
"SDN":{"Happiness":{"2016":4.139},"Economy":{"2016":0.63069},"Family":{"2016":0.81928},"Health":{"2016":0.29759},"Freedom":{"2016":0},"Trust":{"2016":0.10039},"Generosity":{"2016":0.18077},"Residual":{"2016":2.10995}},
"GAB":{"Happiness":{"2016":4.121},"Economy":{"2016":1.15851},"Family":{"2016":0.72368},"Health":{"2016":0.3494},"Freedom":{"2016":0.28098},"Trust":{"2016":0.09314},"Generosity":{"2016":0.06244},"Residual":{"2016":1.45332}},
"MLI":{"Happiness":{"2016":4.073},"Economy":{"2016":0.31292},"Family":{"2016":0.86333},"Health":{"2016":0.16347},"Freedom":{"2016":0.27544},"Trust":{"2016":0.13647},"Generosity":{"2016":0.21064},"Residual":{"2016":2.11087}},
"HTI":{"Happiness":{"2016":4.028},"Economy":{"2016":0.34097},"Family":{"2016":0.29561},"Health":{"2016":0.27494},"Freedom":{"2016":0.12072},"Trust":{"2016":0.14476},"Generosity":{"2016":0.47958},"Residual":{"2016":2.37116}},
"BWA":{"Happiness":{"2016":3.974},"Economy":{"2016":1.09426},"Family":{"2016":0.89186},"Health":{"2016":0.34752},"Freedom":{"2016":0.44089},"Trust":{"2016":0.10769},"Generosity":{"2016":0.12425},"Residual":{"2016":0.96741}},
"COM":{"Happiness":{"2016":3.956},"Economy":{"2016":0.27509},"Family":{"2016":0.60323},"Health":{"2016":0.29981},"Freedom":{"2016":0.15412},"Trust":{"2016":0.18437},"Generosity":{"2016":0.1827},"Residual":{"2016":2.25632}},
"CIV":{"Happiness":{"2016":3.916},"Economy":{"2016":0.55507},"Family":{"2016":0.57576},"Health":{"2016":0.04476},"Freedom":{"2016":0.40663},"Trust":{"2016":0.1553},"Generosity":{"2016":0.20338},"Residual":{"2016":1.97478}},
"KHM":{"Happiness":{"2016":3.907},"Economy":{"2016":0.55604},"Family":{"2016":0.5375},"Health":{"2016":0.42494},"Freedom":{"2016":0.58852},"Trust":{"2016":0.08092},"Generosity":{"2016":0.40339},"Residual":{"2016":1.31573}},
"AGO":{"Happiness":{"2016":3.866},"Economy":{"2016":0.84731},"Family":{"2016":0.66366},"Health":{"2016":0.04991},"Freedom":{"2016":0.00589},"Trust":{"2016":0.08434},"Generosity":{"2016":0.12071},"Residual":{"2016":2.09459}},
"NER":{"Happiness":{"2016":3.856},"Economy":{"2016":0.1327},"Family":{"2016":0.6053},"Health":{"2016":0.26162},"Freedom":{"2016":0.38041},"Trust":{"2016":0.17176},"Generosity":{"2016":0.2097},"Residual":{"2016":2.09469}},
"SSD":{"Happiness":{"2016":3.832},"Economy":{"2016":0.39394},"Family":{"2016":0.18519},"Health":{"2016":0.15781},"Freedom":{"2016":0.19662},"Trust":{"2016":0.13015},"Generosity":{"2016":0.25899},"Residual":{"2016":2.50929}},
"TCD":{"Happiness":{"2016":3.763},"Economy":{"2016":0.42214},"Family":{"2016":0.63178},"Health":{"2016":0.03824},"Freedom":{"2016":0.12807},"Trust":{"2016":0.04952},"Generosity":{"2016":0.18667},"Residual":{"2016":2.30637}},
"BFA":{"Happiness":{"2016":3.739},"Economy":{"2016":0.31995},"Family":{"2016":0.63054},"Health":{"2016":0.21297},"Freedom":{"2016":0.3337},"Trust":{"2016":0.12533},"Generosity":{"2016":0.24353},"Residual":{"2016":1.87319}},
"UGA":{"Happiness":{"2016":3.739},"Economy":{"2016":0.34719},"Family":{"2016":0.90981},"Health":{"2016":0.19625},"Freedom":{"2016":0.43653},"Trust":{"2016":0.06442},"Generosity":{"2016":0.27102},"Residual":{"2016":1.51416}},
"YEM":{"Happiness":{"2016":3.724},"Economy":{"2016":0.57939},"Family":{"2016":0.47493},"Health":{"2016":0.31048},"Freedom":{"2016":0.2287},"Trust":{"2016":0.05892},"Generosity":{"2016":0.09821},"Residual":{"2016":1.97295}},
"MDG":{"Happiness":{"2016":3.695},"Economy":{"2016":0.27954},"Family":{"2016":0.46115},"Health":{"2016":0.37109},"Freedom":{"2016":0.13684},"Trust":{"2016":0.07506},"Generosity":{"2016":0.2204},"Residual":{"2016":2.15075}},
"TZA":{"Happiness":{"2016":3.666},"Economy":{"2016":0.47155},"Family":{"2016":0.77623},"Health":{"2016":0.357},"Freedom":{"2016":0.3176},"Trust":{"2016":0.05099},"Generosity":{"2016":0.31472},"Residual":{"2016":1.37769}},
"LBR":{"Happiness":{"2016":3.622},"Economy":{"2016":0.10706},"Family":{"2016":0.50353},"Health":{"2016":0.23165},"Freedom":{"2016":0.25748},"Trust":{"2016":0.04852},"Generosity":{"2016":0.24063},"Residual":{"2016":2.23284}},
"GIN":{"Happiness":{"2016":3.607},"Economy":{"2016":0.22415},"Family":{"2016":0.3109},"Health":{"2016":0.18829},"Freedom":{"2016":0.30953},"Trust":{"2016":0.1192},"Generosity":{"2016":0.29914},"Residual":{"2016":2.15604}},
"RWA":{"Happiness":{"2016":3.515},"Economy":{"2016":0.32846},"Family":{"2016":0.61586},"Health":{"2016":0.31865},"Freedom":{"2016":0.5432},"Trust":{"2016":0.50521},"Generosity":{"2016":0.23552},"Residual":{"2016":0.96819}},
"BEN":{"Happiness":{"2016":3.484},"Economy":{"2016":0.39499},"Family":{"2016":0.10419},"Health":{"2016":0.21028},"Freedom":{"2016":0.39747},"Trust":{"2016":0.06681},"Generosity":{"2016":0.2018},"Residual":{"2016":2.10812}},
"AFG":{"Happiness":{"2016":3.36},"Economy":{"2016":0.38227},"Family":{"2016":0.11037},"Health":{"2016":0.17344},"Freedom":{"2016":0.1643},"Trust":{"2016":0.07112},"Generosity":{"2016":0.31268},"Residual":{"2016":2.14558}},
"TGO":{"Happiness":{"2016":3.303},"Economy":{"2016":0.28123},"Family":{"2016":0},"Health":{"2016":0.24811},"Freedom":{"2016":0.34678},"Trust":{"2016":0.11587},"Generosity":{"2016":0.17517},"Residual":{"2016":2.1354}},
"SYR":{"Happiness":{"2016":3.069},"Economy":{"2016":0.74719},"Family":{"2016":0.14866},"Health":{"2016":0.62994},"Freedom":{"2016":0.06912},"Trust":{"2016":0.17233},"Generosity":{"2016":0.48397},"Residual":{"2016":0.81789}},
"BDI":{"Happiness":{"2016":2.905},"Economy":{"2016":0.06831},"Family":{"2016":0.23442},"Health":{"2016":0.15747},"Freedom":{"2016":0.0432},"Trust":{"2016":0.09419},"Generosity":{"2016":0.2029},"Residual":{"2016":2.10404}}
}