{"AFG":{"World Giving Index":{"2017":"19"},"helping":{"2017":"41"},"donating":{"2017":"6"},"volunteer":{"2017":"11"}},"ALB":{"World Giving Index":{"2017":"26"},"helping":{"2017":"42"},"donating":{"2017":"28"},"volunteer":{"2017":"7"}},"ALG":{"World Giving Index":{"2017":"28"},"helping":{"2017":"54"},"donating":{"2017":"13"},"volunteer":{"2017":"17"}},"ARG":{"World Giving Index":{"2017":"28"},"helping":{"2017":"52"},"donating":{"2017":"16"},"volunteer":{"2017":"15"}},"ARM":{"World Giving Index":{"2017":"23"},"helping":{"2017":"45"},"donating":{"2017":"15"},"volunteer":{"2017":"9"}},"AUS":{"World Giving Index":{"2017":"59"},"helping":{"2017":"65"},"donating":{"2017":"71"},"volunteer":{"2017":"40"}},"AUT":{"World Giving Index":{"2017":"44"},"helping":{"2017":"52"},"donating":{"2017":"54"},"volunteer":{"2017":"26"}},"AZE":{"World Giving Index":{"2017":"18"},"helping":{"2017":"35"},"donating":{"2017":"8"},"volunteer":{"2017":"12"}},"BHR":{"World Giving Index":{"2017":"53"},"helping":{"2017":"74"},"donating":{"2017":"53"},"volunteer":{"2017":"33"}},"BGD":{"World Giving Index":{"2017":"31"},"helping":{"2017":"57"},"donating":{"2017":"23"},"volunteer":{"2017":"13"}},"BLR":{"World Giving Index":{"2017":"23"},"helping":{"2017":"31"},"donating":{"2017":"21"},"volunteer":{"2017":"19"}},"BEL":{"World Giving Index":{"2017":"41"},"helping":{"2017":"51"},"donating":{"2017":"45"},"volunteer":{"2017":"27"}},"BEN":{"World Giving Index":{"2017":"26"},"helping":{"2017":"48"},"donating":{"2017":"13"},"volunteer":{"2017":"17"}},"BOL":{"World Giving Index":{"2017":"28"},"helping":{"2017":"49"},"donating":{"2017":"15"},"volunteer":{"2017":"21"}},"BIH":{"World Giving Index":{"2017":"28"},"helping":{"2017":"37"},"donating":{"2017":"40"},"volunteer":{"2017":"7"}},"BWA":{"World Giving Index":{"2017":"27"},"helping":{"2017":"59"},"donating":{"2017":"8"},"volunteer":{"2017":"16"}},"BRA":{"World Giving Index":{"2017":"23"},"helping":{"2017":"43"},"donating":{"2017":"14"},"volunteer":{"2017":"13"}},"BGR":{"World Giving Index":{"2017":"22"},"helping":{"2017":"42"},"donating":{"2017":"18"},"volunteer":{"2017":"5"}},"BFA":{"World Giving Index":{"2017":"29"},"helping":{"2017":"56"},"donating":{"2017":"11"},"volunteer":{"2017":"19"}},"KHM":{"World Giving Index":{"2017":"18"},"helping":{"2017":"18"},"donating":{"2017":"30"},"volunteer":{"2017":"6"}},"CMR":{"World Giving Index":{"2017":"34"},"helping":{"2017":"67"},"donating":{"2017":"18"},"volunteer":{"2017":"16"}},"CAN":{"World Giving Index":{"2017":"49"},"helping":{"2017":"57"},"donating":{"2017":"56"},"volunteer":{"2017":"33"}},"CAF":{"World Giving Index":{"2017":"32"},"helping":{"2017":"52"},"donating":{"2017":"18"},"volunteer":{"2017":"27"}},"TCD":{"World Giving Index":{"2017":"27"},"helping":{"2017":"50"},"donating":{"2017":"16"},"volunteer":{"2017":"16"}},"CHL":{"World Giving Index":{"2017":"34"},"helping":{"2017":"54"},"donating":{"2017":"33"},"volunteer":{"2017":"15"}},"CHN":{"World Giving Index":{"2017":"17"},"helping":{"2017":"31"},"donating":{"2017":"14"},"volunteer":{"2017":"7"}},"COL":{"World Giving Index":{"2017":"29"},"helping":{"2017":"56"},"donating":{"2017":"15"},"volunteer":{"2017":"17"}},"COG":{"World Giving Index":{"2017":"24"},"helping":{"2017":"51"},"donating":{"2017":"8"},"volunteer":{"2017":"14"}},"CRI":{"World Giving Index":{"2017":"34"},"helping":{"2017":"59"},"donating":{"2017":"25"},"volunteer":{"2017":"17"}},"HRV":{"World Giving Index":{"2017":"20"},"helping":{"2017":"25"},"donating":{"2017":"25"},"volunteer":{"2017":"11"}},"CYP":{"World Giving Index":{"2017":"43"},"helping":{"2017":"60"},"donating":{"2017":"42"},"volunteer":{"2017":"26"}},"CZE":{"World Giving Index":{"2017":"22"},"helping":{"2017":"26"},"donating":{"2017":"21"},"volunteer":{"2017":"19"}},"CIV":{"World Giving Index":{"2017":"25"},"helping":{"2017":"55"},"donating":{"2017":"12"},"volunteer":{"2017":"7"}},"COD":{"World Giving Index":{"2017":"35"},"helping":{"2017":"56"},"donating":{"2017":"19"},"volunteer":{"2017":"29"}},"DNK":{"World Giving Index":{"2017":"46"},"helping":{"2017":"58"},"donating":{"2017":"56"},"volunteer":{"2017":"23"}},"DOM":{"World Giving Index":{"2017":"39"},"helping":{"2017":"64"},"donating":{"2017":"20"},"volunteer":{"2017":"32"}},"ECU":{"World Giving Index":{"2017":"24"},"helping":{"2017":"40"},"donating":{"2017":"13"},"volunteer":{"2017":"18"}},"EGY":{"World Giving Index":{"2017":"26"},"helping":{"2017":"57"},"donating":{"2017":"14"},"volunteer":{"2017":"6"}},"SLV":{"World Giving Index":{"2017":"22"},"helping":{"2017":"39"},"donating":{"2017":"10"},"volunteer":{"2017":"15"}},"EST":{"World Giving Index":{"2017":"26"},"helping":{"2017":"34"},"donating":{"2017":"27"},"volunteer":{"2017":"16"}},"ETH":{"World Giving Index":{"2017":"27"},"helping":{"2017":"43"},"donating":{"2017":"17"},"volunteer":{"2017":"23"}},"FIN":{"World Giving Index":{"2017":"40"},"helping":{"2017":"53"},"donating":{"2017":"39"},"volunteer":{"2017":"26"}},"FRA":{"World Giving Index":{"2017":"32"},"helping":{"2017":"37"},"donating":{"2017":"27"},"volunteer":{"2017":"31"}},"GAB":{"World Giving Index":{"2017":"24"},"helping":{"2017":"54"},"donating":{"2017":"9"},"volunteer":{"2017":"10"}},"GMB":{"World Giving Index":{"2017":"44"},"helping":{"2017":"74"},"donating":{"2017":"28"},"volunteer":{"2017":"30"}},"GEO":{"World Giving Index":{"2017":"24"},"helping":{"2017":"47"},"donating":{"2017":"6"},"volunteer":{"2017":"17"}},"DEU":{"World Giving Index":{"2017":"46"},"helping":{"2017":"58"},"donating":{"2017":"55"},"volunteer":{"2017":"26"}},"GHA":{"World Giving Index":{"2017":"42"},"helping":{"2017":"62"},"donating":{"2017":"30"},"volunteer":{"2017":"36"}},"GRC":{"World Giving Index":{"2017":"17"},"helping":{"2017":"36"},"donating":{"2017":"7"},"volunteer":{"2017":"7"}},"GTM":{"World Giving Index":{"2017":"34"},"helping":{"2017":"51"},"donating":{"2017":"21"},"volunteer":{"2017":"28"}},"GIN":{"World Giving Index":{"2017":"32"},"helping":{"2017":"52"},"donating":{"2017":"22"},"volunteer":{"2017":"24"}},"HTI":{"World Giving Index":{"2017":"49"},"helping":{"2017":"62"},"donating":{"2017":"54"},"volunteer":{"2017":"31"}},"HND":{"World Giving Index":{"2017":"39"},"helping":{"2017":"54"},"donating":{"2017":"31"},"volunteer":{"2017":"32"}},"HKG":{"World Giving Index":{"2017":"44"},"helping":{"2017":"60"},"donating":{"2017":"55"},"volunteer":{"2017":"19"}},"HUN":{"World Giving Index":{"2017":"23"},"helping":{"2017":"36"},"donating":{"2017":"22"},"volunteer":{"2017":"12"}},"ISL":{"World Giving Index":{"2017":"48"},"helping":{"2017":"50"},"donating":{"2017":"65"},"volunteer":{"2017":"27"}},"IND":{"World Giving Index":{"2017":"22"},"helping":{"2017":"31"},"donating":{"2017":"20"},"volunteer":{"2017":"15"}},"IDN":{"World Giving Index":{"2017":"59"},"helping":{"2017":"46"},"donating":{"2017":"78"},"volunteer":{"2017":"53"}},"IRN":{"World Giving Index":{"2017":"45"},"helping":{"2017":"61"},"donating":{"2017":"53"},"volunteer":{"2017":"20"}},"IRQ":{"World Giving Index":{"2017":"43"},"helping":{"2017":"81"},"donating":{"2017":"29"},"volunteer":{"2017":"19"}},"IRL":{"World Giving Index":{"2017":"56"},"helping":{"2017":"64"},"donating":{"2017":"64"},"volunteer":{"2017":"40"}},"ISR":{"World Giving Index":{"2017":"42"},"helping":{"2017":"50"},"donating":{"2017":"53"},"volunteer":{"2017":"23"}},"ITA":{"World Giving Index":{"2017":"33"},"helping":{"2017":"46"},"donating":{"2017":"35"},"volunteer":{"2017":"17"}},"JAM":{"World Giving Index":{"2017":"36"},"helping":{"2017":"63"},"donating":{"2017":"15"},"volunteer":{"2017":"29"}},"JPN":{"World Giving Index":{"2017":"22"},"helping":{"2017":"23"},"donating":{"2017":"18"},"volunteer":{"2017":"23"}},"JOR":{"World Giving Index":{"2017":"30"},"helping":{"2017":"68"},"donating":{"2017":"13"},"volunteer":{"2017":"9"}},"KAZ":{"World Giving Index":{"2017":"28"},"helping":{"2017":"35"},"donating":{"2017":"32"},"volunteer":{"2017":"16"}},"KEN":{"World Giving Index":{"2017":"54"},"helping":{"2017":"72"},"donating":{"2017":"46"},"volunteer":{"2017":"45"}},"XKX":{"World Giving Index":{"2017":"33"},"helping":{"2017":"50"},"donating":{"2017":"40"},"volunteer":{"2017":"10"}},"KWT":{"World Giving Index":{"2017":"43"},"helping":{"2017":"80"},"donating":{"2017":"39"},"volunteer":{"2017":"11"}},"KGZ":{"World Giving Index":{"2017":"36"},"helping":{"2017":"52"},"donating":{"2017":"38"},"volunteer":{"2017":"18"}},"LAO":{"World Giving Index":{"2017":"20"},"helping":{"2017":"22"},"donating":{"2017":"33"},"volunteer":{"2017":"4"}},"LVA":{"World Giving Index":{"2017":"19"},"helping":{"2017":"28"},"donating":{"2017":"21"},"volunteer":{"2017":"9"}},"LBN":{"World Giving Index":{"2017":"28"},"helping":{"2017":"49"},"donating":{"2017":"24"},"volunteer":{"2017":"12"}},"LSO":{"World Giving Index":{"2017":"28"},"helping":{"2017":"58"},"donating":{"2017":"5"},"volunteer":{"2017":"20"}},"LBR":{"World Giving Index":{"2017":"47"},"helping":{"2017":"80"},"donating":{"2017":"14"},"volunteer":{"2017":"47"}},"LBY":{"World Giving Index":{"2017":"45"},"helping":{"2017":"83"},"donating":{"2017":"28"},"volunteer":{"2017":"24"}},"LTU":{"World Giving Index":{"2017":"19"},"helping":{"2017":""},"donating":{"2017":"19"},"volunteer":{"2017":"18"}},"LUX":{"World Giving Index":{"2017":"41"},"helping":{"2017":"40"},"donating":{"2017":"50"},"volunteer":{"2017":"33"}},"MKD":{"World Giving Index":{"2017":"20"},"helping":{"2017":"30"},"donating":{"2017":"26"},"volunteer":{"2017":"5"}},"MDG":{"World Giving Index":{"2017":"27"},"helping":{"2017":"39"},"donating":{"2017":"12"},"volunteer":{"2017":"31"}},"MWI":{"World Giving Index":{"2017":"35"},"helping":{"2017":"66"},"donating":{"2017":"15"},"volunteer":{"2017":"26"}},"MLI":{"World Giving Index":{"2017":"28"},"helping":{"2017":"52"},"donating":{"2017":"11"},"volunteer":{"2017":"20"}},"MLT":{"World Giving Index":{"2017":"47"},"helping":{"2017":"53"},"donating":{"2017":"64"},"volunteer":{"2017":"25"}},"MRT":{"World Giving Index":{"2017":"20"},"helping":{"2017":"37"},"donating":{"2017":"8"},"volunteer":{"2017":"14"}},"MUS":{"World Giving Index":{"2017":"46"},"helping":{"2017":"57"},"donating":{"2017":"42"},"volunteer":{"2017":"38"}},"MEX":{"World Giving Index":{"2017":"24"},"helping":{"2017":"45"},"donating":{"2017":"13"},"volunteer":{"2017":"14"}},"MDA":{"World Giving Index":{"2017":"27"},"helping":{"2017":"45"},"donating":{"2017":"24"},"volunteer":{"2017":"13"}},"MNG":{"World Giving Index":{"2017":"39"},"helping":{"2017":"41"},"donating":{"2017":"41"},"volunteer":{"2017":"36"}},"MNE":{"World Giving Index":{"2017":"24"},"helping":{"2017":"38"},"donating":{"2017":"25"},"volunteer":{"2017":"9"}},"MAR":{"World Giving Index":{"2017":"26"},"helping":{"2017":"65"},"donating":{"2017":"5"},"volunteer":{"2017":"9"}},"MOZ":{"World Giving Index":{"2017":"29"},"helping":{"2017":"50"},"donating":{"2017":"11"},"volunteer":{"2017":"27"}},"MMR":{"World Giving Index":{"2017":"54"},"helping":{"2017":"40"},"donating":{"2017":"88"},"volunteer":{"2017":"34"}},"NAM":{"World Giving Index":{"2017":"32"},"helping":{"2017":"64"},"donating":{"2017":"10"},"volunteer":{"2017":"21"}},"NPL":{"World Giving Index":{"2017":"37"},"helping":{"2017":"50"},"donating":{"2017":"33"},"volunteer":{"2017":"27"}},"NLD":{"World Giving Index":{"2017":"51"},"helping":{"2017":"52"},"donating":{"2017":"66"},"volunteer":{"2017":"37"}},"NZL":{"World Giving Index":{"2017":"58"},"helping":{"2017":"66"},"donating":{"2017":"68"},"volunteer":{"2017":"40"}},"NIC":{"World Giving Index":{"2017":"33"},"helping":{"2017":"52"},"donating":{"2017":"26"},"volunteer":{"2017":"22"}},"NER":{"World Giving Index":{"2017":"32"},"helping":{"2017":"66"},"donating":{"2017":"10"},"volunteer":{"2017":"20"}},"NGA":{"World Giving Index":{"2017":"48"},"helping":{"2017":"71"},"donating":{"2017":"36"},"volunteer":{"2017":"37"}},"NOR":{"World Giving Index":{"2017":"50"},"helping":{"2017":"54"},"donating":{"2017":"65"},"volunteer":{"2017":"32"}},"PAK":{"World Giving Index":{"2017":"28"},"helping":{"2017":"43"},"donating":{"2017":"27"},"volunteer":{"2017":"13"}},"PSE":{"World Giving Index":{"2017":"17"},"helping":{"2017":"37"},"donating":{"2017":"7"},"volunteer":{"2017":"9"}},"PAN":{"World Giving Index":{"2017":"30"},"helping":{"2017":"48"},"donating":{"2017":"20"},"volunteer":{"2017":"21"}},"PRY":{"World Giving Index":{"2017":"34"},"helping":{"2017":"53"},"donating":{"2017":"28"},"volunteer":{"2017":"22"}},"PER":{"World Giving Index":{"2017":"27"},"helping":{"2017":"47"},"donating":{"2017":"15"},"volunteer":{"2017":"20"}},"PHL":{"World Giving Index":{"2017":"28"},"helping":{"2017":"44"},"donating":{"2017":"13"},"volunteer":{"2017":"28"}},"POL":{"World Giving Index":{"2017":"24"},"helping":{"2017":"34"},"donating":{"2017":"24"},"volunteer":{"2017":"15"}},"PRT":{"World Giving Index":{"2017":"28"},"helping":{"2017":"50"},"donating":{"2017":"20"},"volunteer":{"2017":"15"}},"KOR":{"World Giving Index":{"2017":"34"},"helping":{"2017":"47"},"donating":{"2017":"40"},"volunteer":{"2017":"15"}},"ROU":{"World Giving Index":{"2017":"27"},"helping":{"2017":"54"},"donating":{"2017":"20"},"volunteer":{"2017":"6"}},"RUS":{"World Giving Index":{"2017":"25"},"helping":{"2017":"44"},"donating":{"2017":"21"},"volunteer":{"2017":"11"}},"RWA":{"World Giving Index":{"2017":"26"},"helping":{"2017":"39"},"donating":{"2017":"22"},"volunteer":{"2017":"18"}},"SAU":{"World Giving Index":{"2017":"37"},"helping":{"2017":"74"},"donating":{"2017":"26"},"volunteer":{"2017":"12"}},"SEN":{"World Giving Index":{"2017":"28"},"helping":{"2017":"54"},"donating":{"2017":"16"},"volunteer":{"2017":"15"}},"SRB":{"World Giving Index":{"2017":"21"},"helping":{"2017":"34"},"donating":{"2017":"24"},"volunteer":{"2017":"6"}},"SLE":{"World Giving Index":{"2017":"47"},"helping":{"2017":"80"},"donating":{"2017":"23"},"volunteer":{"2017":"37"}},"SGP":{"World Giving Index":{"2017":"54"},"helping":{"2017":"67"},"donating":{"2017":"58"},"volunteer":{"2017":"39"}},"SVK":{"World Giving Index":{"2017":"28"},"helping":{"2017":"32"},"donating":{"2017":"31"},"volunteer":{"2017":"22"}},"SVN":{"World Giving Index":{"2017":"39"},"helping":{"2017":"47"},"donating":{"2017":"35"},"volunteer":{"2017":"35"}},"ZAF":{"World Giving Index":{"2017":"41"},"helping":{"2017":"72"},"donating":{"2017":"17"},"volunteer":{"2017":"34"}},"SSD":{"World Giving Index":{"2017":"39"},"helping":{"2017":"60"},"donating":{"2017":"29"},"volunteer":{"2017":"29"}},"ESP":{"World Giving Index":{"2017":"36"},"helping":{"2017":"56"},"donating":{"2017":"35"},"volunteer":{"2017":"17"}},"LKA":{"World Giving Index":{"2017":"45"},"helping":{"2017":"52"},"donating":{"2017":"39"},"volunteer":{"2017":"45"}},"SWE":{"World Giving Index":{"2017":"41"},"helping":{"2017":"52"},"donating":{"2017":"57"},"volunteer":{"2017":"13"}},"CHE":{"World Giving Index":{"2017":"45"},"helping":{"2017":"40"},"donating":{"2017":"60"},"volunteer":{"2017":"37"}},"TWN":{"World Giving Index":{"2017":"34"},"helping":{"2017":"49"},"donating":{"2017":"33"},"volunteer":{"2017":"19"}},"TJK":{"World Giving Index":{"2017":"42"},"helping":{"2017":"59"},"donating":{"2017":"32"},"volunteer":{"2017":"36"}},"TZA":{"World Giving Index":{"2017":"28"},"helping":{"2017":"47"},"donating":{"2017":"30"},"volunteer":{"2017":"8"}},"THA":{"World Giving Index":{"2017":"34"},"helping":{"2017":"36"},"donating":{"2017":"53"},"volunteer":{"2017":"12"}},"TGO":{"World Giving Index":{"2017":"24"},"helping":{"2017":"46"},"donating":{"2017":"11"},"volunteer":{"2017":"14"}},"TTO":{"World Giving Index":{"2017":"46"},"helping":{"2017":"70"},"donating":{"2017":"37"},"volunteer":{"2017":"31"}},"TUN":{"World Giving Index":{"2017":"20"},"helping":{"2017":"44"},"donating":{"2017":"7"},"volunteer":{"2017":"8"}},"TUR":{"World Giving Index":{"2017":"20"},"helping":{"2017":"40"},"donating":{"2017":"12"},"volunteer":{"2017":"9"}},"TKM":{"World Giving Index":{"2017":"40"},"helping":{"2017":"48"},"donating":{"2017":"37"},"volunteer":{"2017":"35"}},"UGA":{"World Giving Index":{"2017":"39"},"helping":{"2017":"67"},"donating":{"2017":"23"},"volunteer":{"2017":"26"}},"UKR":{"World Giving Index":{"2017":"29"},"helping":{"2017":"42"},"donating":{"2017":"29"},"volunteer":{"2017":"15"}},"ARE":{"World Giving Index":{"2017":"51"},"helping":{"2017":"68"},"donating":{"2017":"62"},"volunteer":{"2017":"23"}},"GBR":{"World Giving Index":{"2017":"55"},"helping":{"2017":"63"},"donating":{"2017":"68"},"volunteer":{"2017":"33"}},"USA":{"World Giving Index":{"2017":"58"},"helping":{"2017":"72"},"donating":{"2017":"61"},"volunteer":{"2017":"39"}},"URY":{"World Giving Index":{"2017":"30"},"helping":{"2017":"49"},"donating":{"2017":"25"},"volunteer":{"2017":"15"}},"UZB":{"World Giving Index":{"2017":"36"},"helping":{"2017":"51"},"donating":{"2017":"38"},"volunteer":{"2017":"20"}},"VEN":{"World Giving Index":{"2017":"26"},"helping":{"2017":"51"},"donating":{"2017":"11"},"volunteer":{"2017":"15"}},"YEM":{"World Giving Index":{"2017":"15"},"helping":{"2017":"36"},"donating":{"2017":"2"},"volunteer":{"2017":"6"}},"ZMB":{"World Giving Index":{"2017":"46"},"helping":{"2017":"70"},"donating":{"2017":"35"},"volunteer":{"2017":"34"}},"ZWE":{"World Giving Index":{"2017":"30"},"helping":{"2017":"61"},"donating":{"2017":"10"},"volunteer":{"2017":"18"}}}